{
    "type": "devsdream:crafting_shaped_nbt",
    "pattern": [
        "-#-",
        "#D#",
        "###"
    ],
    "key": {
        "#": {
            "item": "minecraft:rabbit_hide"
        },
        "-": {
            "item": "minecraft:string"
        },
        "D": {
            "item": "minecraft:light_blue_dye"
        }
    },
    "result": {
        "item": "minecraft:bundle",
        "nbt": "{tcc:{id:\"dyed_bundle\",color:\"light_blue\"},CustomModelData:330006,display:{Name:'{\"translate\":\"item.tcc.dyed_bundle.light_blue\",\"italic\":false}',Lore:['{\"translate\":\"pack.tcc\",\"color\":\"#008725\",\"italic\":true}']}}"
    }
}